pyControl4/__init__.py
pyControl4/account.py
pyControl4/alarm.py
pyControl4/blind.py
pyControl4/climate.py
pyControl4/director.py
pyControl4/error_handling.py
pyControl4/fan.py
pyControl4/light.py
pyControl4/relay.py
pyControl4/room.py
pyControl4/websocket.py
pycontrol4-1.5.0.dist-info/licenses/LICENSE
pycontrol4-1.5.0.dist-info/METADATA
pycontrol4-1.5.0.dist-info/WHEEL
pycontrol4-1.5.0.dist-info/top_level.txt
pycontrol4-1.5.0.dist-info/RECORD
