Metadata-Version: 2.4
Name: pyControl4
Version: 1.5.0
Summary: Python 3 asyncio package for interacting with Control4 systems
Home-page: https://github.com/lawtancool/pyControl4
Author: lawtancool
Author-email: contact@lawrencetan.ca
Classifier: Programming Language :: Python :: 3
Classifier: License :: OSI Approved :: Apache Software License
Classifier: Operating System :: OS Independent
Requires-Python: >=3.6
License-File: LICENSE
Requires-Dist: aiohttp
Requires-Dist: xmltodict
Requires-Dist: python-socketio-v4
Requires-Dist: websocket-client
Dynamic: author
Dynamic: author-email
Dynamic: classifier
Dynamic: description
Dynamic: description-content-type
Dynamic: home-page
Dynamic: license-file
Dynamic: requires-dist
Dynamic: requires-python
Dynamic: summary
